{"cameraMode":{"drawMode":0,"name":"Shaded","section":"Shading Mode"},"sceneLighting":true,"audioPlay":false,"sceneViewState":{"m_AlwaysRefresh":false,"showFog":true,"showSkybox":true,"showFlares":true,"showImageEffects":true,"showParticleSystems":true,"showVisualEffectGraphs":true,"m_FxEnabled":false},"in2DMode":false,"pivot":{"x":18.177288055419923,"y":7.276102066040039,"z":349.55419921875},"rotation":{"x":-0.25889602303504946,"y":0.23998485505580903,"z":-0.06657526642084122,"w":-0.9332459568977356},"size":8.81109619140625,"orthographic":false}